SECFE/FSE.py
SECFE/SEFD.py
SECFE/SKiS.py
SECFE/__init__.py
SECFE/__version__.py
SECFE/utils.py
SECFE-0.3.2.dist-info/LICENSE.txt
SECFE-0.3.2.dist-info/METADATA
SECFE-0.3.2.dist-info/WHEEL
SECFE-0.3.2.dist-info/top_level.txt
SECFE-0.3.2.dist-info/RECORD
