Metadata-Version: 2.1
Name: SECFE
Version: 0.3.2
Summary: A Python package for downloading and extracting information from SEC Filings. As a note, this package requires lxml functions that may not run on Mac OS. 
Home-page: https://github.com/arechiga-code/SECFE
Author: Alan Arechiga
Author-email: aarechiga1@fordham.edu
License: MIT
Keywords: SEC Edgar,stocks,data,finance,filings,extractor
Platform: UNKNOWN
Classifier: Development Status :: 3 - Alpha
Classifier: Intended Audience :: Developers
Classifier: Intended Audience :: Financial and Insurance Industry
Classifier: Topic :: Software Development :: Libraries :: Python Modules
Classifier: Topic :: Office/Business :: Financial
Classifier: License :: OSI Approved :: MIT License
Classifier: Programming Language :: Python :: 3
Classifier: Programming Language :: Python :: 3.7
Classifier: Programming Language :: Python :: 3.8
Classifier: Programming Language :: Python :: 3.9
License-File: LICENSE.txt
Requires-Dist: requests
Requires-Dist: lxml
Requires-Dist: beautifulsoup4
